_pfifo.cpython-37m-darwin.so
pfifo/__init__.py
pfifo/include/pfifo/pfifo.hpp
pfifo/include/pfifo/reader.hpp
pfifo/include/pfifo/writer.hpp
pfifo-1.1.7.data/headers/pfifo.hpp
pfifo-1.1.7.data/headers/reader.hpp
pfifo-1.1.7.data/headers/writer.hpp
pfifo-1.1.7.dist-info/LICENSE
pfifo-1.1.7.dist-info/METADATA
pfifo-1.1.7.dist-info/WHEEL
pfifo-1.1.7.dist-info/top_level.txt
pfifo-1.1.7.dist-info/RECORD
