Metadata-Version: 2.1
Name: pfifo
Version: 1.1.7
Summary: POSIX fifo wrapper for Python
Home-page: https://github.com/ktnyt/pfifo
Author: Kotone Itaya
Author-email: kotone@sfc.keio.ac.jp
License: Apache
Platform: UNKNOWN
Requires-Dist: pybind11 (>=2.2)
